[{"name":"configs","qualifiedName":"configs","href":"configs_configs/configs_configs-library.html","type":"library","overriddenDepth":0,"packageName":"document_scanner_flutter"},{"name":"ScannerConfigsAndroid","qualifiedName":"configs.ScannerConfigsAndroid","href":"configs_configs/ScannerConfigsAndroid-class.html","type":"enum","overriddenDepth":0,"packageName":"document_scanner_flutter","enclosedBy":{"name":"configs","type":"library"}},{"name":"toString","qualifiedName":"configs.ScannerConfigsAndroid.toString","href":"configs_configs/ScannerConfigsAndroid/toString.html","type":"method","overriddenDepth":1,"packageName":"document_scanner_flutter","enclosedBy":{"name":"ScannerConfigsAndroid","type":"enum"}},{"name":"ScannerFileSource","qualifiedName":"configs.ScannerFileSource","href":"configs_configs/ScannerFileSource-class.html","type":"enum","overriddenDepth":0,"packageName":"document_scanner_flutter","enclosedBy":{"name":"configs","type":"library"}},{"name":"toString","qualifiedName":"configs.ScannerFileSource.toString","href":"configs_configs/ScannerFileSource/toString.html","type":"method","overriddenDepth":1,"packageName":"document_scanner_flutter","enclosedBy":{"name":"ScannerFileSource","type":"enum"}},{"name":"document_scanner_flutter","qualifiedName":"document_scanner_flutter","href":"document_scanner_flutter/document_scanner_flutter-library.html","type":"library","overriddenDepth":0,"packageName":"document_scanner_flutter"},{"name":"DocumentScannerFlutter","qualifiedName":"document_scanner_flutter.DocumentScannerFlutter","href":"document_scanner_flutter/DocumentScannerFlutter-class.html","type":"class","overriddenDepth":0,"packageName":"document_scanner_flutter","enclosedBy":{"name":"document_scanner_flutter","type":"library"}},{"name":"DocumentScannerFlutter","qualifiedName":"document_scanner_flutter.DocumentScannerFlutter.DocumentScannerFlutter","href":"document_scanner_flutter/DocumentScannerFlutter/DocumentScannerFlutter.html","type":"constructor","overriddenDepth":0,"packageName":"document_scanner_flutter","enclosedBy":{"name":"DocumentScannerFlutter","type":"class"}},{"name":"launch","qualifiedName":"document_scanner_flutter.DocumentScannerFlutter.launch","href":"document_scanner_flutter/DocumentScannerFlutter/launch.html","type":"method","overriddenDepth":0,"packageName":"document_scanner_flutter","enclosedBy":{"name":"DocumentScannerFlutter","type":"class"}},{"name":"launchForPdf","qualifiedName":"document_scanner_flutter.DocumentScannerFlutter.launchForPdf","href":"document_scanner_flutter/DocumentScannerFlutter/launchForPdf.html","type":"method","overriddenDepth":0,"packageName":"document_scanner_flutter","enclosedBy":{"name":"DocumentScannerFlutter","type":"class"}},{"name":"pdf_generator_gallery","qualifiedName":"pdf_generator_gallery","href":"screens_pdf_generator_gallery/screens_pdf_generator_gallery-library.html","type":"library","overriddenDepth":0,"packageName":"document_scanner_flutter"},{"name":"FilePicker","qualifiedName":"pdf_generator_gallery.FilePicker","href":"screens_pdf_generator_gallery/FilePicker.html","type":"typedef","overriddenDepth":0,"packageName":"document_scanner_flutter","enclosedBy":{"name":"pdf_generator_gallery","type":"library"}},{"name":"PdfGeneratotGallery","qualifiedName":"pdf_generator_gallery.PdfGeneratotGallery","href":"screens_pdf_generator_gallery/PdfGeneratotGallery-class.html","type":"class","overriddenDepth":0,"packageName":"document_scanner_flutter","enclosedBy":{"name":"pdf_generator_gallery","type":"library"}},{"name":"PdfGeneratotGallery","qualifiedName":"pdf_generator_gallery.PdfGeneratotGallery.PdfGeneratotGallery","href":"screens_pdf_generator_gallery/PdfGeneratotGallery/PdfGeneratotGallery.html","type":"constructor","overriddenDepth":0,"packageName":"document_scanner_flutter","enclosedBy":{"name":"PdfGeneratotGallery","type":"class"}},{"name":"createState","qualifiedName":"pdf_generator_gallery.PdfGeneratotGallery.createState","href":"screens_pdf_generator_gallery/PdfGeneratotGallery/createState.html","type":"method","overriddenDepth":1,"packageName":"document_scanner_flutter","enclosedBy":{"name":"PdfGeneratotGallery","type":"class"}},{"name":"filePicker","qualifiedName":"pdf_generator_gallery.PdfGeneratotGallery.filePicker","href":"screens_pdf_generator_gallery/PdfGeneratotGallery/filePicker.html","type":"property","overriddenDepth":0,"packageName":"document_scanner_flutter","enclosedBy":{"name":"PdfGeneratotGallery","type":"class"}},{"name":"photo_viewer","qualifiedName":"photo_viewer","href":"screens_photo_viewer/screens_photo_viewer-library.html","type":"library","overriddenDepth":0,"packageName":"document_scanner_flutter"},{"name":"PhotoViewer","qualifiedName":"photo_viewer.PhotoViewer","href":"screens_photo_viewer/PhotoViewer-class.html","type":"class","overriddenDepth":0,"packageName":"document_scanner_flutter","enclosedBy":{"name":"photo_viewer","type":"library"}},{"name":"PhotoViewer","qualifiedName":"photo_viewer.PhotoViewer.PhotoViewer","href":"screens_photo_viewer/PhotoViewer/PhotoViewer.html","type":"constructor","overriddenDepth":0,"packageName":"document_scanner_flutter","enclosedBy":{"name":"PhotoViewer","type":"class"}},{"name":"build","qualifiedName":"photo_viewer.PhotoViewer.build","href":"screens_photo_viewer/PhotoViewer/build.html","type":"method","overriddenDepth":1,"packageName":"document_scanner_flutter","enclosedBy":{"name":"PhotoViewer","type":"class"}},{"name":"galleryItems","qualifiedName":"photo_viewer.PhotoViewer.galleryItems","href":"screens_photo_viewer/PhotoViewer/galleryItems.html","type":"property","overriddenDepth":0,"packageName":"document_scanner_flutter","enclosedBy":{"name":"PhotoViewer","type":"class"}},{"name":"selectedItemIndex","qualifiedName":"photo_viewer.PhotoViewer.selectedItemIndex","href":"screens_photo_viewer/PhotoViewer/selectedItemIndex.html","type":"property","overriddenDepth":0,"packageName":"document_scanner_flutter","enclosedBy":{"name":"PhotoViewer","type":"class"}}]
